sanic_aioja/__init__.py
sanic_aioja/defaultglobals.py
sanic_aioja/undefined.py
sanic_aioja-0.0.1.dist-info/LICENSE
sanic_aioja-0.0.1.dist-info/METADATA
sanic_aioja-0.0.1.dist-info/WHEEL
sanic_aioja-0.0.1.dist-info/top_level.txt
sanic_aioja-0.0.1.dist-info/RECORD
